icreateExe/__init__.py
icreateExe/icreateExe.py
icreate_exe-1.0.0.dist-info/LICENSE
icreate_exe-1.0.0.dist-info/METADATA
icreate_exe-1.0.0.dist-info/WHEEL
icreate_exe-1.0.0.dist-info/entry_points.txt
icreate_exe-1.0.0.dist-info/top_level.txt
icreate_exe-1.0.0.dist-info/RECORD
