Metadata-Version: 2.1
Name: icreate-exe
Version: 1.0.0
Summary: Приложение для создания exe файла из .py
Author: Ilia Miheev
Author-email: strict-swept-unify@duck.com
License: MIT
License-File: LICENSE
Requires-Dist: pyinstaller
